circle/__init__.py
circle/api_requestor.py
circle/circle_object.py
circle/circle_response.py
circle/error.py
circle/error_classes.py
circle/http_client.py
circle/object_classes.py
circle/resources/__init__.py
circle/resources/abstract/__init__.py
circle/resources/abstract/api_resource.py
circle/resources/abstract/createable.py
circle/resources/abstract/listable.py
circle/resources/abstract/nested_resource_class_methods.py
circle/resources/abstract/retrievable.py
circle/resources/abstract/updateable.py
circle/resources/ach.py
circle/resources/balances.py
circle/resources/business_account_deposit_addresses.py
circle/resources/card.py
circle/resources/error_object.py
circle/resources/master_wallet.py
circle/resources/message.py
circle/resources/mock_wire_payment.py
circle/resources/mocks_ach_account.py
circle/resources/notification.py
circle/resources/payment.py
circle/resources/payout.py
circle/resources/public_key.py
circle/resources/reversal.py
circle/resources/settlement.py
circle/resources/subscription.py
circle/resources/transfer.py
circle/resources/wire.py
circle/resources/wire_instruction.py
circle/util.py
circle_python-0.0.44.dist-info/LICENSE
circle_python-0.0.44.dist-info/WHEEL
circle_python-0.0.44.dist-info/METADATA
circle_python-0.0.44.dist-info/RECORD
