Metadata-Version: 2.1
Name: circle-python
Version: 0.0.44
Summary: 
License: MIT
Author: Crawford Leeds
Author-email: crawford@crawfordleeds.com
Requires-Python: >=3.6,<4.0
Classifier: Development Status :: 2 - Pre-Alpha
Classifier: Intended Audience :: Developers
Classifier: License :: OSI Approved :: MIT License
Classifier: Natural Language :: English
Classifier: Programming Language :: Python :: 3
Classifier: Programming Language :: Python :: 3.10
Classifier: Programming Language :: Python :: 3.6
Classifier: Programming Language :: Python :: 3.7
Classifier: Programming Language :: Python :: 3.8
Classifier: Programming Language :: Python :: 3.9
Requires-Dist: aws-sns-message-validator2 (>=0.0.1,<0.0.2)
Requires-Dist: requests (>=2.20.0)
Requires-Dist: urllib3 (>=1.26,<2.0)
